data_prep_kit/__init__.py
data_prep_kit/categorical_encoding.py
data_prep_kit/data_reading.py
data_prep_kit/data_summary.py
data_prep_kit/missing_values.py
DataPrekit-0.1.dist-info/METADATA
DataPrekit-0.1.dist-info/WHEEL
DataPrekit-0.1.dist-info/top_level.txt
DataPrekit-0.1.dist-info/RECORD
