Metadata-Version: 2.1
Name: DataPrekit
Version: 0.1
Summary: A toolkit for preprocessing datasets for machine learning and data analysis.
Home-page: UNKNOWN
Author: aseel thobaity
Author-email: a9ile20@gmail.com
License: UNKNOWN
Platform: UNKNOWN
Classifier: Development Status :: 3 - Alpha
Classifier: Intended Audience :: Developers
Classifier: License :: OSI Approved :: MIT License
Classifier: Programming Language :: Python :: 3
Classifier: Programming Language :: Python :: 3.7
Classifier: Programming Language :: Python :: 3.8
Classifier: Programming Language :: Python :: 3.9
Requires-Dist: pandas
Requires-Dist: numpy
